{
  "entry_14980": {
    "ipa": "p\u028e\u00e6\u02d0na\u0320",
    "lat": "7.0442231",
    "tppsr": "pl\u032ea\u0364\u0304na",
    "taxon": "Montbovon",
    "lon": "46.4882147",
    "canton": "FR"
  },
  "entry_14954": {
    "ipa": "p\u028e\u025b\u0303\u0129\u0349n\u0103\u0320",
    "lat": "6.742199",
    "tppsr": "pl\u032e\u00e8\u0303\u0129\u0331n\u0103",
    "taxon": "Montpreveyres",
    "lon": "46.582048",
    "canton": "VD"
  },
  "entry_14963": {
    "ipa": "ple\u02d0n\u0250\u0349",
    "lat": "7.1463639",
    "tppsr": "pl\u1e17n\u0227\u0331",
    "taxon": "Orsi\u00e8res",
    "lon": "46.0308094",
    "canton": "VS"
  },
  "entry_15000": {
    "ipa": "p\u00e7\u025b\u0303n",
    "lat": "7.3367958",
    "tppsr": "p\u00e7\u0311\u00e8\u0303n",
    "taxon": "Court",
    "lon": "47.239562",
    "canton": "JU"
  },
  "entry_14993": {
    "ipa": "p\u00e7\u00e6\u02d0na\u0320\u0349",
    "lat": "6.7246751",
    "tppsr": "p\u00e7\u0311a\u0364\u0304na\u0331",
    "taxon": "Noiraigue",
    "lon": "46.9562832",
    "canton": "NE"
  },
  "entry_14959": {
    "ipa": "pl\u025b\u0303\u02d0na\u0320",
    "lat": "6.8047071",
    "tppsr": "pl\u00e8\u0304\u0303na",
    "taxon": "St-Gingolph",
    "lon": "46.3931549",
    "canton": "VS"
  },
  "entry_14971": {
    "ipa": "pl\u025b\u0303\u0129\u0349na\u0320",
    "lat": "7.4580917",
    "tppsr": "pl\u00e8\u0303\u0129\u0331na",
    "taxon": "Gr\u00f4ne",
    "lon": "46.2508508",
    "canton": "VS"
  },
  "entry_15004": {
    "ipa": "pj\u025b\u0303n",
    "lat": "7.0413733",
    "tppsr": "py\u00e8\u0303n",
    "taxon": "Courtedoux",
    "lon": "47.4101588",
    "canton": "JU"
  },
  "entry_14988": {
    "ipa": "p\u00e7a\u0320\u02d0\u025b\u0349na\u0320\u0349",
    "lat": "6.837028",
    "tppsr": "p\u00e7\u0311\u0101\u00e8\u0331na\u0331",
    "taxon": "Boudry",
    "lon": "46.950218",
    "canton": "NE"
  },
  "entry_14998": {
    "ipa": "p\u00e7\u00e3\u0320\u1ebd\u031e\u0129\u0349n",
    "lat": "7.284885",
    "tppsr": "p\u00e7\u0311\u00e3\u1ebd\u0129\u0331n",
    "taxon": "Plagne",
    "lon": "47.1874392",
    "canton": "JU"
  },
  "entry_14981": {
    "ipa": "p\u029d\u025b\u02d0na\u0320",
    "lat": "7.1214922",
    "tppsr": "py\u0306\u1e15na",
    "taxon": "Arconciel",
    "lon": "46.7473353",
    "canton": "FR"
  },
  "entry_15002": {
    "ipa": "pj\u025b\u0306n",
    "lat": "7.2946",
    "tppsr": "py\u0115\u0300n",
    "taxon": "Develier",
    "lon": "47.356623",
    "canton": "JU"
  },
  "entry_14972": {
    "ipa": "pl\u025b\u0303\u0129\u014b\u0349na\u0349",
    "lat": "7.4963134",
    "tppsr": "pl\u00e8\u0303\u0129\u1e49\u0307n\u00e0\u0331",
    "taxon": "\u00c9vol\u00e8ne",
    "lon": "46.1125593",
    "canton": "VS"
  },
  "entry_15003": {
    "ipa": "pj\u025b\u0306n",
    "lat": "7.027788",
    "tppsr": "py\u0115\u0300n",
    "taxon": "Cerlatez",
    "lon": "47.243446",
    "canton": "JU"
  },
  "entry_14955": {
    "ipa": "p\u028e\u0254\u0306\u0301\u012dn\u0103",
    "lat": "6.536765",
    "tppsr": "pl\u032e\u014f\u0329\u0300\u012dn\u1eb1",
    "taxon": "Charnex",
    "lon": "46.5613135",
    "canton": "VD"
  },
  "entry_14952": {
    "ipa": "p\u028e\u025b\u02d0na\u0320",
    "lat": "6.639461",
    "tppsr": "pl\u032e\u1e15na",
    "taxon": "Villars-le-Terroir",
    "lon": "46.657569",
    "canton": "VD"
  },
  "entry_14969": {
    "ipa": "pl\u02b2\u025b\u0303\u0129\u0349na\u0320",
    "lat": "7.4081901",
    "tppsr": "pl\u0311\u00e8\u0303\u0129\u0331na",
    "taxon": "Ayent",
    "lon": "46.2771888",
    "canton": "VS"
  },
  "entry_14996": {
    "ipa": "pj\u025b\u0303n",
    "lat": "7.2159458",
    "tppsr": "py\u00e8\u0303n",
    "taxon": "Lamboing",
    "lon": "47.0995336",
    "canton": "JU"
  },
  "entry_14957": {
    "ipa": "p\u03b8\u02e1a\u0320\u0349\u025b\u0303na\u0320",
    "lat": "7.158066",
    "tppsr": "p\u1e63\u030da\u0331\u00e8\u0303na",
    "taxon": "Ormont-Dessus",
    "lon": "46.3514789",
    "canton": "VD"
  },
  "entry_14979": {
    "ipa": "p\u00e7\u025b\u0303na\u0320",
    "lat": "6.9273567",
    "tppsr": "p\u00e7\u0311\u00e8\u0303na",
    "taxon": "Semsalves",
    "lon": "46.5731935",
    "canton": "FR"
  },
  "entry_14999": {
    "ipa": "pj\u025b\u0303n",
    "lat": "7.1785922",
    "tppsr": "py\u00e8\u0303n",
    "taxon": "Sombeval",
    "lon": "47.1957904",
    "canton": "JU"
  },
  "entry_14984": {
    "ipa": "pj\u025b\u0301i\u0349na\u0320",
    "lat": "6.990713",
    "tppsr": "py\u00e8\u0329i\u0331na",
    "taxon": "Dompierre",
    "lon": "46.8520788",
    "canton": "FR"
  },
  "entry_14944": {
    "ipa": "p\u028ee\u02d0na\u0320",
    "lat": "6.6362255",
    "tppsr": "pl\u032e\u1e17na",
    "taxon": "Vaugondry",
    "lon": "46.8467152",
    "canton": "VD"
  },
  "entry_14970": {
    "ipa": "pl\u025b\u0303n\u0103\u0320",
    "lat": "7.5473871",
    "tppsr": "pl\u00e8\u0303n\u0103",
    "taxon": "Mi\u00e8ge",
    "lon": "46.3119557",
    "canton": "VS"
  },
  "entry_14960": {
    "ipa": "p\u03b8\u025b\u0306i\u0349n\u0103\u0320",
    "lat": "6.9459222",
    "tppsr": "p\u1e63\u0115\u0300i\u0331n\u0103",
    "taxon": "Collombey",
    "lon": "46.2679563",
    "canton": "VS"
  },
  "entry_14978": {
    "ipa": "p\u028e\u00e3\u0320na\u0320",
    "lat": "6.244375",
    "tppsr": "pl\u032e\u00e3na",
    "taxon": "Hermance",
    "lon": "46.302258",
    "canton": "GE"
  },
  "entry_14949": {
    "ipa": "p\u028e\u00e3\u0320na\u0320",
    "lat": "6.176213",
    "tppsr": "pl\u032e\u00e3na",
    "taxon": "Commugny",
    "lon": "46.320929",
    "canton": "VD"
  },
  "entry_14989": {
    "ipa": "p\u00e7\u00e6\u02d0na\u0320",
    "lat": "6.8624613",
    "tppsr": "p\u00e7\u0311a\u0364\u0304na",
    "taxon": "Corcelles",
    "lon": "46.9830376",
    "canton": "NE"
  },
  "entry_14992": {
    "ipa": "pl\u00e6\u0303na\u0320",
    "lat": "6.489867",
    "tppsr": "pla\u0364\u0303na",
    "taxon": "C\u00f4te-aux-F\u00e9es",
    "lon": "46.866729",
    "canton": "NE"
  },
  "entry_14994": {
    "ipa": "p\u00e7\u00e6\u02d0na\u0320",
    "lat": "6.7022949",
    "tppsr": "p\u00e7\u0311a\u0364\u0304na",
    "taxon": "Chaux-du-Milieu",
    "lon": "47.0127695",
    "canton": "NE"
  },
  "french": "(est) pleine",
  "entry_14945": {
    "ipa": "p\u028ee\u031e\u02d0na\u0320",
    "lat": "6.4590043",
    "tppsr": "pl\u032e\u0113na",
    "taxon": "L'Auberson",
    "lon": "46.8178516",
    "canton": "VD"
  },
  "entry_14977": {
    "ipa": "p\u028e\u00e3\u0320na\u0320\u0349",
    "lat": "6.1832454",
    "tppsr": "pl\u032e\u00e3na\u0331",
    "taxon": "Veyrier",
    "lon": "46.16778",
    "canton": "GE"
  },
  "entry_14987": {
    "ipa": "p\u00e7e\u02d0na\u0320",
    "lat": "6.746543",
    "tppsr": "p\u00e7\u0311\u1e17na",
    "taxon": "Montalchez",
    "lon": "46.8977631",
    "canton": "NE"
  },
  "entry_14968": {
    "ipa": "pl\u025b\u0303\u02d0na\u0320",
    "lat": "7.3509003",
    "tppsr": "pl\u00e8\u0304\u0303na",
    "taxon": "Savi\u00e8se",
    "lon": "46.2535376",
    "canton": "VS"
  },
  "entry_14990": {
    "ipa": "pj\u0252\u031d\u02d0\u025b\u0349n",
    "lat": "7.066851",
    "tppsr": "pya\u0366\u0304\u00e8\u0331n",
    "taxon": "Landeron",
    "lon": "47.055508",
    "canton": "NE"
  },
  "entry_14962": {
    "ipa": "ple\u031e\u02d0na\u0320\u0349",
    "lat": "7.073483",
    "tppsr": "pl\u0113na\u0331",
    "taxon": "Martigny",
    "lon": "46.101706",
    "canton": "VS"
  },
  "entry_14983": {
    "ipa": "p\u00e7j\u1ebd\u0129\u0349na\u0320",
    "lat": "7.1238357",
    "tppsr": "p\u00e7\u0311y\u00e9\u0303\u0129\u0331na",
    "taxon": "Courtepin",
    "lon": "46.8652994",
    "canton": "FR"
  },
  "entry_14961": {
    "ipa": "p\u03b8\u025b\u0303n\u0251\u0306",
    "lat": "6.8693248",
    "tppsr": "p\u1e63\u00e8\u0303n\u1eaf",
    "taxon": "Champ\u00e9ry",
    "lon": "46.1778839",
    "canton": "VS"
  },
  "entry_14948": {
    "ipa": "p\u028e\u025b\u02d0na\u0320\u0349",
    "lat": "6.2585316",
    "tppsr": "pl\u032e\u1e15na\u0331",
    "taxon": "Longirod",
    "lon": "46.4944282",
    "canton": "VD"
  },
  "entry_14956": {
    "ipa": "p\u028e\u025b\u0303\u02d0na\u0320",
    "lat": "6.9290939",
    "tppsr": "pl\u032e\u00e8\u0304\u0303na",
    "taxon": "Roche",
    "lon": "46.3614134",
    "canton": "VD"
  },
  "entry_14995": {
    "ipa": "p\u028e\u026a\u0303n\u025b\u0349",
    "lat": "6.6661454",
    "tppsr": "pl\u032e\u00ec\u0303n\u00e8\u0331",
    "taxon": "Cerneux-P\u00eaquignot",
    "lon": "47.0169066",
    "canton": "NE"
  },
  "entry_14986": {
    "ipa": "pj\u025b\u0303\u0129\u0349na\u0320",
    "lat": "7.1134823",
    "tppsr": "py\u00e8\u0303\u0129\u0331na",
    "taxon": "Sugiez",
    "lon": "46.9624815",
    "canton": "FR"
  },
  "entry_14947": {
    "ipa": "p\u028e\u1ebd\u031e\u0301\u0129\u0349n\u0103\u0320",
    "lat": "6.2358557",
    "tppsr": "pl\u032e\u1ebd\u0329\u0129\u0331n\u0103",
    "taxon": "Le Sentier",
    "lon": "46.6122131",
    "canton": "VD"
  },
  "entry_14997": {
    "ipa": "pj\u025b\u0303n",
    "lat": "7.250875",
    "tppsr": "py\u00e8\u0303n",
    "taxon": "Orvin",
    "lon": "47.139974",
    "canton": "JU"
  },
  "entry_14965": {
    "ipa": "ple\u02d0n\u02d0\u0103\u0320",
    "lat": "7.1147534",
    "tppsr": "pl\u1e17n\u0304\u0103",
    "taxon": "Fully",
    "lon": "46.1385798",
    "canton": "VS"
  },
  "entry_14991": {
    "ipa": "p\u00e7\u00e6\u02d0n",
    "lat": "6.956111",
    "tppsr": "p\u00e7\u0311a\u0364\u0304n",
    "taxon": "Savagnier",
    "lon": "47.050961",
    "canton": "NE"
  },
  "entry_14975": {
    "ipa": "p\u028e\u00e3\u0320na\u0320\u0349",
    "lat": "6.084291",
    "tppsr": "pl\u032e\u00e3na\u0331",
    "taxon": "Vernier",
    "lon": "46.217026",
    "canton": "GE"
  },
  "entry_14964": {
    "ipa": "pl\u02b2e\u02d0na\u0320\u0349",
    "lat": "7.265844",
    "tppsr": "pl\u0311\u1e17na\u0331",
    "taxon": "Lourtier",
    "lon": "46.049002",
    "canton": "VS"
  },
  "entry_14985": {
    "ipa": "p\u028e\u025b\u0303\u0129\u0349na\u0320",
    "lat": "6.8070537",
    "tppsr": "pl\u032e\u00e8\u0303\u0129\u0331na",
    "taxon": "Murist",
    "lon": "46.7898177",
    "canton": "FR"
  },
  "latin": "plena",
  "entry_14951": {
    "ipa": "p\u00e7e\u02d0na\u0320",
    "lat": "6.5189028",
    "tppsr": "p\u00e7\u0311\u1e17na",
    "taxon": "Arnex",
    "lon": "46.6980681",
    "canton": "VD"
  },
  "entry_14976": {
    "ipa": "p\u028e\u025b\u0303\u02d0n\u00f2\u031d\u0349",
    "lat": "6.0355571",
    "tppsr": "pl\u032e\u00e8\u0304\u0303n\u00f2\u0331",
    "taxon": "Laconnex",
    "lon": "46.1557721",
    "canton": "GE"
  },
  "entry_14973": {
    "ipa": "p\u029f\u025b\u0303\u0129\u0349na\u0320",
    "lat": "7.5763635",
    "tppsr": "p\u0142\u00e8\u0303\u0129\u0331na",
    "taxon": "Grimentz",
    "lon": "46.1801158",
    "canton": "VS"
  },
  "entry_15001": {
    "ipa": "pj\u025b\u0306n",
    "lat": "7.471447",
    "tppsr": "py\u0115\u0300n",
    "taxon": "Vermes",
    "lon": "47.329461",
    "canton": "JU"
  },
  "entry_14958": {
    "ipa": "p\u03b8a\u0320\u035ce na\u0320",
    "lat": "7.1285556",
    "tppsr": "p\u1e63a\u035c\u00e9 na",
    "taxon": "Ch\u00e2teau-d'Oex",
    "lon": "46.4732964",
    "canton": "VD"
  },
  "entry_14966": {
    "ipa": "pf\u00e6\u0306i\u0349na\u0320",
    "lat": "7.3083227",
    "tppsr": "pfa\u0364\u0306i\u0331na",
    "taxon": "Conthey",
    "lon": "46.2334191",
    "canton": "VS"
  },
  "entry_14967": {
    "ipa": "ple\u031eina\u0320",
    "lat": "7.3047431",
    "tppsr": "pleina",
    "taxon": "Nendaz",
    "lon": "46.1855093",
    "canton": "VS"
  },
  "entry_14946": {
    "ipa": "p\u028e\u00e9\u02d0n\u0103\u0320",
    "lat": "6.3796258",
    "tppsr": "pl\u032e\u1e17\u0329n\u0103",
    "taxon": "Vallorbe",
    "lon": "46.711414",
    "canton": "VD"
  },
  "entry_14982": {
    "ipa": "p\u028e\u025b\u0303\u0129\u0349na\u0320",
    "lat": "7.0698887",
    "tppsr": "pl\u032e\u00e8\u0303\u0129\u0331na",
    "taxon": "Avry-sur-Matran",
    "lon": "46.7895993",
    "canton": "FR"
  },
  "entry_14943": {
    "ipa": "p\u00e7\u025b\u0303\u0129\u0349na\u0320\u0349",
    "lat": "6.9069294",
    "tppsr": "p\u00e7\u0311\u00e8\u0303\u0129\u0331na\u0331",
    "taxon": "Chevroux",
    "lon": "46.8883582",
    "canton": "VD"
  },
  "entry_14974": {
    "ipa": "p\u028e\u00e3\u0320\u0301na\u0320",
    "lat": "6.1235296",
    "tppsr": "pl\u032e\u00e3\u0329na",
    "taxon": "Collex",
    "lon": "46.2761547",
    "canton": "GE"
  },
  "entry_14953": {
    "ipa": "p\u029d\u025b\u0303\u02d0\u0129\u0349na\u0320\u0349",
    "lat": "6.7383916",
    "tppsr": "py\u0306\u00e8\u0304\u0303\u0129\u0331na\u0331",
    "taxon": "Prahins",
    "lon": "46.7331778",
    "canton": "VD"
  },
  "entry_14950": {
    "ipa": "p\u00e7\u025b\u02d0na\u0320\u0349",
    "lat": "6.4816044",
    "tppsr": "p\u00e7\u0311\u1e15na\u0331",
    "taxon": "Vullierens",
    "lon": "46.5727052",
    "canton": "VD"
  }
}