{
  "entry_1243": {
    "ipa": "fre\u031e\u02d0da\u0320",
    "lat": "6.4590043",
    "tppsr": "fr\u0113da",
    "taxon": "L'Auberson",
    "lon": "46.8178516",
    "canton": "VD"
  },
  "entry_1293": {
    "ipa": "fr\u00e6\u0306d\u025b",
    "lat": "6.6661454",
    "tppsr": "fra\u0364\u0306d\u00e8",
    "taxon": "Cerneux-P\u00eaquignot",
    "lon": "47.0169066",
    "canton": "NE"
  },
  "entry_1287": {
    "ipa": "fr\u01fd\u02d0da\u0320",
    "lat": "6.8624613",
    "tppsr": "fra\u0329\u0364\u0304da",
    "taxon": "Corcelles",
    "lon": "46.9830376",
    "canton": "NE"
  },
  "entry_1259": {
    "ipa": "fr\u0251\u02d0d\u0259\u0349",
    "lat": "6.8693248",
    "tppsr": "fr\u0101\u0301d\u0117\u0331",
    "taxon": "Champ\u00e9ry",
    "lon": "46.1778839",
    "canton": "VS"
  },
  "latin": "frigida",
  "entry_1302": {
    "ipa": "frw\u0103\u0320d",
    "lat": "7.0413733",
    "tppsr": "frw\u0103d",
    "taxon": "Courtedoux",
    "lon": "47.4101588",
    "canton": "JU"
  },
  "entry_1249": {
    "ipa": "fra\u0320\u02d0\u025b\u0349d\u025b\u0349\u0308",
    "lat": "6.5189028",
    "tppsr": "fr\u0101\u00e8\u0331d\u00eb\u0331",
    "taxon": "Arnex",
    "lon": "46.6980681",
    "canton": "VD"
  },
  "entry_1275": {
    "ipa": "fr\u00e6\u02d0da\u0320\u0349",
    "lat": "6.1832454",
    "tppsr": "fra\u0364\u0304da\u0331",
    "taxon": "Veyrier",
    "lon": "46.16778",
    "canton": "GE"
  },
  "entry_1250": {
    "ipa": "b\u025b\u0303\u0129\u0349 fra\u0320i\u0349d\u0259\u0349",
    "lat": "6.639461",
    "tppsr": "b\u00e8\u0303\u0129\u0331 frai\u0331d\u0117\u0331",
    "taxon": "Villars-le-Terroir",
    "lon": "46.657569",
    "canton": "VD"
  },
  "entry_1294": {
    "ipa": "fr\u025bd",
    "lat": "7.2159458",
    "tppsr": "fr\u00e8d",
    "taxon": "Lamboing",
    "lon": "47.0995336",
    "canton": "JU"
  },
  "entry_1242": {
    "ipa": "fr\u00e6\u02d0d\u025b\u0349",
    "lat": "6.6362255",
    "tppsr": "fra\u0364\u0304d\u00e8\u0331",
    "taxon": "Vaugondry",
    "lon": "46.8467152",
    "canton": "VD"
  },
  "entry_1252": {
    "ipa": "fra\u02d0\u025b\u0349d\u0259\u0349",
    "lat": "6.742199",
    "tppsr": "fr\u0101\u0300\u00e8\u0331d\u0117\u0331",
    "taxon": "Montpreveyres",
    "lon": "46.582048",
    "canton": "VD"
  },
  "entry_1263": {
    "ipa": "fr\u00e6id\u0259\u0349",
    "lat": "7.1147534",
    "tppsr": "fra\u0364id\u0117\u0331",
    "taxon": "Fully",
    "lon": "46.1385798",
    "canton": "VS"
  },
  "entry_1270": {
    "ipa": "fr\u0115i\u0349d\u026a\u0349\u0308",
    "lat": "7.4963134",
    "tppsr": "fr\u0115\u0301i\u0331d\u00ef\u0331",
    "taxon": "\u00c9vol\u00e8ne",
    "lon": "46.1125593",
    "canton": "VS"
  },
  "entry_1266": {
    "ipa": "fri\u02d0d\u025b\u0349",
    "lat": "7.3509003",
    "tppsr": "fr\u012bd\u00e8\u0331",
    "taxon": "Savi\u00e8se",
    "lon": "46.2535376",
    "canton": "VS"
  },
  "entry_1253": {
    "ipa": "fr\u0252\u031d\u02d0j\u0349d\u0259\u0349",
    "lat": "6.536765",
    "tppsr": "fra\u0366\u0304y\u0331d\u0117\u0331",
    "taxon": "Charnex",
    "lon": "46.5613135",
    "canton": "VD"
  },
  "entry_1285": {
    "ipa": "f\u0280a\u0320\u02d0e\u0349da\u0320\u0349",
    "lat": "6.746543",
    "tppsr": "f\u1e59\u0101\u00e9\u0331da\u0331",
    "taxon": "Montalchez",
    "lon": "46.8977631",
    "canton": "NE"
  },
  "entry_1273": {
    "ipa": "fr\u00e6\u02d0da\u0320\u0349",
    "lat": "6.084291",
    "tppsr": "fra\u0364\u0304da\u0331",
    "taxon": "Vernier",
    "lon": "46.217026",
    "canton": "GE"
  },
  "entry_1277": {
    "ipa": "fra\u0320\u02d0d\u0259\u0349",
    "lat": "6.9273567",
    "tppsr": "fr\u0101d\u0117\u0331",
    "taxon": "Semsalves",
    "lon": "46.5731935",
    "canton": "FR"
  },
  "entry_1245": {
    "ipa": "fr\u025b\u02d0i\u0349da\u0320\u0349",
    "lat": "6.2358557",
    "tppsr": "fr\u1e15i\u0331da\u0331",
    "taxon": "Le Sentier",
    "lon": "46.6122131",
    "canton": "VD"
  },
  "entry_1241": {
    "ipa": "fr\u0251\u02d0d\u025b\u0349\u0308",
    "lat": "6.9069294",
    "tppsr": "fr\u0101\u0301d\u00eb\u0331",
    "taxon": "Chevroux",
    "lon": "46.8883582",
    "canton": "VD"
  },
  "entry_1254": {
    "ipa": "fr\u0251\u02d0\u025b\u0349d\u0259\u0349",
    "lat": "6.9290939",
    "tppsr": "fr\u0101\u0301\u00e8\u0331d\u0117\u0331",
    "taxon": "Roche",
    "lon": "46.3614134",
    "canton": "VD"
  },
  "entry_1267": {
    "ipa": "fr\u0115id\u025b\u0349\u0308",
    "lat": "7.4081901",
    "tppsr": "fr\u0115\u0301id\u00eb\u0331",
    "taxon": "Ayent",
    "lon": "46.2771888",
    "canton": "VS"
  },
  "entry_1282": {
    "ipa": "fr\u0251\u02d0\u025b\u0349d",
    "lat": "6.990713",
    "tppsr": "fr\u0101\u0301\u00e8\u0331d",
    "taxon": "Dompierre",
    "lon": "46.8520788",
    "canton": "FR"
  },
  "entry_1251": {
    "ipa": "fr\u00e6\u02d0d\u0259\u0349",
    "lat": "6.7383916",
    "tppsr": "fra\u0364\u0304d\u0117\u0331",
    "taxon": "Prahins",
    "lon": "46.7331778",
    "canton": "VD"
  },
  "entry_1295": {
    "ipa": "fr\u00e6i\u0349d",
    "lat": "7.250875",
    "tppsr": "fra\u0364i\u0331d",
    "taxon": "Orvin",
    "lon": "47.139974",
    "canton": "JU"
  },
  "french": "froide",
  "entry_1276": {
    "ipa": "fr\u025b\u02d0da\u0320\u0349",
    "lat": "6.244375",
    "tppsr": "fr\u1e15da\u0331",
    "taxon": "Hermance",
    "lon": "46.302258",
    "canton": "GE"
  },
  "entry_1247": {
    "ipa": "fr\u025b\u02d0da\u0320\u0349",
    "lat": "6.176213",
    "tppsr": "fr\u1e15da\u0331",
    "taxon": "Commugny",
    "lon": "46.320929",
    "canton": "VD"
  },
  "entry_1284": {
    "ipa": "fr\u025b\u02d0d\u0259\u0349",
    "lat": "7.1134823",
    "tppsr": "fr\u1e15d\u0117\u0331",
    "taxon": "Sugiez",
    "lon": "46.9624815",
    "canton": "FR"
  },
  "entry_1279": {
    "ipa": "fr\u00e6\u02d0d\u0259\u0349",
    "lat": "7.1214922",
    "tppsr": "fra\u0364\u0304d\u0117\u0331",
    "taxon": "Arconciel",
    "lon": "46.7473353",
    "canton": "FR"
  },
  "entry_1268": {
    "ipa": "fr\u012dde\u031d\u0349",
    "lat": "7.5473871",
    "tppsr": "fr\u012dde\u0331\u0365",
    "taxon": "Mi\u00e8ge",
    "lon": "46.3119557",
    "canton": "VS"
  },
  "entry_1248": {
    "ipa": "fr\u0251\u02d0\u025b\u0349d\u0259\u0349",
    "lat": "6.4816044",
    "tppsr": "fr\u0101\u0301\u00e8\u0331d\u0117\u0331",
    "taxon": "Vullierens",
    "lon": "46.5727052",
    "canton": "VD"
  },
  "entry_1292": {
    "ipa": "f\u0280\u025b\u0306da\u0320",
    "lat": "6.7022949",
    "tppsr": "f\u1e59\u0115\u0300da",
    "taxon": "Chaux-du-Milieu",
    "lon": "47.0127695",
    "canton": "NE"
  },
  "entry_1269": {
    "ipa": "fre\u031ei\u0349d\u0259\u0349",
    "lat": "7.4580917",
    "tppsr": "frei\u0331d\u0117\u0331",
    "taxon": "Gr\u00f4ne",
    "lon": "46.2508508",
    "canton": "VS"
  },
  "entry_1283": {
    "ipa": "fr\u0252\u031d\u02d0d\u0259\u0349",
    "lat": "6.8070537",
    "tppsr": "fra\u0366\u0304d\u0117\u0331",
    "taxon": "Murist",
    "lon": "46.7898177",
    "canton": "FR"
  },
  "entry_1300": {
    "ipa": "fr\u00e6\u0306d",
    "lat": "7.2946",
    "tppsr": "fra\u0364\u0306d",
    "taxon": "Develier",
    "lon": "47.356623",
    "canton": "JU"
  },
  "entry_1272": {
    "ipa": "fr\u025bda\u0320\u0349",
    "lat": "6.1235296",
    "tppsr": "fr\u00e8da\u0331",
    "taxon": "Collex",
    "lon": "46.2761547",
    "canton": "GE"
  },
  "entry_1258": {
    "ipa": "fr\u0251\u02d0d\u0259\u0349",
    "lat": "6.9459222",
    "tppsr": "fr\u0101\u0301d\u0117\u0331",
    "taxon": "Collombey",
    "lon": "46.2679563",
    "canton": "VS"
  },
  "entry_1274": {
    "ipa": "fra\u0320\u02d0da\u0320\u0349",
    "lat": "6.0355571",
    "tppsr": "fr\u0101da\u0331",
    "taxon": "Laconnex",
    "lon": "46.1557721",
    "canton": "GE"
  },
  "entry_1281": {
    "ipa": "fra\u02d0e\u031e\u0349d",
    "lat": "7.1238357",
    "tppsr": "fr\u0101\u0300e\u0331d",
    "taxon": "Courtepin",
    "lon": "46.8652994",
    "canton": "FR"
  },
  "entry_1301": {
    "ipa": "frw\u0103\u0320d",
    "lat": "7.027788",
    "tppsr": "frw\u0103d",
    "taxon": "Cerlatez",
    "lon": "47.243446",
    "canton": "JU"
  },
  "entry_1289": {
    "ipa": "fre\u02d0d",
    "lat": "6.956111",
    "tppsr": "fr\u1e17d",
    "taxon": "Savagnier",
    "lon": "47.050961",
    "canton": "NE"
  },
  "entry_1286": {
    "ipa": "fra\u0320\u02d0\u025b\u0349da\u0320\u0349",
    "lat": "6.837028",
    "tppsr": "fr\u0101\u00e8\u0331da\u0331",
    "taxon": "Boudry",
    "lon": "46.950218",
    "canton": "NE"
  },
  "entry_1264": {
    "ipa": "fr\u025b\u0306i\u0349d\u0259\u0349",
    "lat": "7.3083227",
    "tppsr": "fr\u0115\u0300i\u0331d\u0117\u0331",
    "taxon": "Conthey",
    "lon": "46.2334191",
    "canton": "VS"
  },
  "entry_1246": {
    "ipa": "fra\u0320\u035c\u00e9\u031e\u02d0da\u0320\u0349",
    "lat": "6.2585316",
    "tppsr": "fra\u035c\u0113\u0329da\u0331",
    "taxon": "Longirod",
    "lon": "46.4944282",
    "canton": "VD"
  },
  "entry_1255": {
    "ipa": "fra\u0320\u035c\u025bd\u0259\u0349",
    "lat": "7.158066",
    "tppsr": "fra\u035c\u00e8d\u0117\u0331",
    "taxon": "Ormont-Dessus",
    "lon": "46.3514789",
    "canton": "VD"
  },
  "entry_1299": {
    "ipa": "fr\u00e6\u0306d",
    "lat": "7.471447",
    "tppsr": "fra\u0364\u0306d",
    "taxon": "Vermes",
    "lon": "47.329461",
    "canton": "JU"
  },
  "entry_1296": {
    "ipa": "fra\u0320\u02d0\u025b\u0349d",
    "lat": "7.284885",
    "tppsr": "fr\u0101\u00e8\u0331d",
    "taxon": "Plagne",
    "lon": "47.1874392",
    "canton": "JU"
  },
  "entry_1291": {
    "ipa": "fr\u025b\u02d0d\u0103\u0320",
    "lat": "6.7246751",
    "tppsr": "fr\u1e15d\u0103",
    "taxon": "Noiraigue",
    "lon": "46.9562832",
    "canton": "NE"
  },
  "entry_1262": {
    "ipa": "fr\u0103i\u0349d\u0259\u0349",
    "lat": "7.265844",
    "tppsr": "fr\u1eb1i\u0331d\u0117\u0331",
    "taxon": "Lourtier",
    "lon": "46.049002",
    "canton": "VS"
  },
  "entry_1271": {
    "ipa": "fri\u02d0de\u031d\u0349",
    "lat": "7.5763635",
    "tppsr": "fr\u012bde\u0331\u0365",
    "taxon": "Grimentz",
    "lon": "46.1801158",
    "canton": "VS"
  },
  "entry_1257": {
    "ipa": "fr\u00e6i\u0349d\u0259\u0349",
    "lat": "6.8047071",
    "tppsr": "fra\u0364i\u0331d\u0117\u0331",
    "taxon": "St-Gingolph",
    "lon": "46.3931549",
    "canton": "VS"
  },
  "entry_1244": {
    "ipa": "fr\u00e6\u02d0da\u0320\u0349",
    "lat": "6.3796258",
    "tppsr": "fra\u0364\u0304da\u0331",
    "taxon": "Vallorbe",
    "lon": "46.711414",
    "canton": "VD"
  },
  "entry_1260": {
    "ipa": "fr\u0115\u031ei\u0349d\u02d0\u0259\u0349",
    "lat": "7.073483",
    "tppsr": "fr\u0115i\u0331d\u0304\u0117\u0331",
    "taxon": "Martigny",
    "lon": "46.101706",
    "canton": "VS"
  },
  "entry_1288": {
    "ipa": "fr\u0252\u031d\u02d0\u025b\u0349d",
    "lat": "7.066851",
    "tppsr": "fra\u0366\u0304\u00e8\u0331d",
    "taxon": "Landeron",
    "lon": "47.055508",
    "canton": "NE"
  },
  "entry_1298": {
    "ipa": "fr\u025b\u02d0d",
    "lat": "7.3367958",
    "tppsr": "fr\u1e15d",
    "taxon": "Court",
    "lon": "47.239562",
    "canton": "JU"
  },
  "entry_1261": {
    "ipa": "fr\u00e6\u0306i\u0349d\u025b\u0349\u0308",
    "lat": "7.1463639",
    "tppsr": "fra\u0364\u0306i\u0331d\u00eb\u0331",
    "taxon": "Orsi\u00e8res",
    "lon": "46.0308094",
    "canton": "VS"
  },
  "entry_1278": {
    "ipa": "fr\u00e6\u02d0d\u0259\u0349",
    "lat": "7.0442231",
    "tppsr": "fra\u0364\u0304d\u0117\u0331",
    "taxon": "Montbovon",
    "lon": "46.4882147",
    "canton": "FR"
  },
  "entry_1297": {
    "ipa": "fr\u025b\u0306d",
    "lat": "7.1785922",
    "tppsr": "fr\u0115\u0300d",
    "taxon": "Sombeval",
    "lon": "47.1957904",
    "canton": "JU"
  },
  "entry_1290": {
    "ipa": "fr\u025b\u0306da\u0320\u0349",
    "lat": "6.489867",
    "tppsr": "fr\u0115\u0300da\u0331",
    "taxon": "C\u00f4te-aux-F\u00e9es",
    "lon": "46.866729",
    "canton": "NE"
  },
  "entry_1280": {
    "ipa": "fra\u0320\u02d0\u025b\u0349d\u0259\u0349",
    "lat": "7.0698887",
    "tppsr": "fr\u0101\u00e8\u0331d\u0117\u0331",
    "taxon": "Avry-sur-Matran",
    "lon": "46.7895993",
    "canton": "FR"
  },
  "entry_1265": {
    "ipa": "fre\u031ei\u0349di\u0349",
    "lat": "7.3047431",
    "tppsr": "frei\u0331di\u0331",
    "taxon": "Nendaz",
    "lon": "46.1855093",
    "canton": "VS"
  },
  "entry_1256": {
    "ipa": "fr\u00e6\u0306id\u0259\u0349",
    "lat": "7.1285556",
    "tppsr": "fra\u0364\u0306id\u0117\u0331",
    "taxon": "Ch\u00e2teau-d'Oex",
    "lon": "46.4732964",
    "canton": "VD"
  }
}