{
  "entry_22186": {
    "ipa": "vi\u02d0\u028e",
    "lat": "6.7022949",
    "tppsr": "v\u012bl\u032e",
    "taxon": "Chaux-du-Milieu",
    "lon": "47.0127695",
    "canton": "NE"
  },
  "entry_22165": {
    "ipa": "vj\u014fu\u0349",
    "lat": "7.5763635",
    "tppsr": "vy\u014f\u0301\u028b\u0331",
    "taxon": "Grimentz",
    "lon": "46.1801158",
    "canton": "VS"
  },
  "entry_22194": {
    "ipa": "ve\u031e\u02d0j",
    "lat": "7.2946",
    "tppsr": "v\u0113y",
    "taxon": "Develier",
    "lon": "47.356623",
    "canton": "JU"
  },
  "entry_22142": {
    "ipa": "vi\u02d0j\u00f2\u031d\u0349",
    "lat": "6.4816044",
    "tppsr": "v\u012by\u00f2\u0331",
    "taxon": "Vullierens",
    "lon": "46.5727052",
    "canton": "VD"
  },
  "entry_22177": {
    "ipa": "vi\u02d0\u028eu\u0349",
    "lat": "6.8070537",
    "tppsr": "v\u012bl\u032e\u028b\u0331",
    "taxon": "Murist",
    "lon": "46.7898177",
    "canton": "FR"
  },
  "entry_22156": {
    "ipa": "vj\u0254\u02d0",
    "lat": "7.265844",
    "tppsr": "vy\u1e51",
    "taxon": "Lourtier",
    "lon": "46.049002",
    "canton": "VS"
  },
  "latin": "veclu, -cla",
  "entry_22179": {
    "ipa": "vi\u02d0\u028e\u00f2\u031d\u0349",
    "lat": "6.746543",
    "tppsr": "v\u012bl\u032e\u00f2\u0331",
    "taxon": "Montalchez",
    "lon": "46.8977631",
    "canton": "NE"
  },
  "entry_22138": {
    "ipa": "vi\u02d0lu\u0349",
    "lat": "6.3796258",
    "tppsr": "v\u012bl\u028b\u0331",
    "taxon": "Vallorbe",
    "lon": "46.711414",
    "canton": "VD"
  },
  "entry_22196": {
    "ipa": "ve\u02d0j",
    "lat": "7.0413733",
    "tppsr": "v\u1e17y",
    "taxon": "Courtedoux",
    "lon": "47.4101588",
    "canton": "JU"
  },
  "entry_22188": {
    "ipa": "ve\u031d\u02d0j",
    "lat": "7.2159458",
    "tppsr": "ve\u0365\u0304y",
    "taxon": "Lamboing",
    "lon": "47.0995336",
    "canton": "JU"
  },
  "entry_22176": {
    "ipa": "v\u026a\u02d0\u028eu\u0349",
    "lat": "6.990713",
    "tppsr": "v\u012b\u0300l\u032e\u028b\u0331",
    "taxon": "Dompierre",
    "lon": "46.8520788",
    "canton": "FR"
  },
  "entry_22193": {
    "ipa": "ve\u02d0j",
    "lat": "7.471447",
    "tppsr": "v\u1e17y",
    "taxon": "Vermes",
    "lon": "47.329461",
    "canton": "JU"
  },
  "entry_22161": {
    "ipa": "vj\u0254\u0306",
    "lat": "7.4081901",
    "tppsr": "vy\u014f\u0300",
    "taxon": "Ayent",
    "lon": "46.2771888",
    "canton": "VS"
  },
  "entry_22152": {
    "ipa": "j\u0153\u0306y\u0349",
    "lat": "6.9459222",
    "tppsr": "y\u0153\u0306\u0300u\u0331",
    "taxon": "Collombey",
    "lon": "46.2679563",
    "canton": "VS"
  },
  "entry_22144": {
    "ipa": "vi\u02d0\u028eo\u031d\u0349",
    "lat": "6.639461",
    "tppsr": "v\u012bl\u032eo\u0331",
    "taxon": "Villars-le-Terroir",
    "lon": "46.657569",
    "canton": "VD"
  },
  "entry_22184": {
    "ipa": "vi\u02d0\u029d\u016d",
    "lat": "6.489867",
    "tppsr": "v\u012by\u0306\u028b\u0306",
    "taxon": "C\u00f4te-aux-F\u00e9es",
    "lon": "46.866729",
    "canton": "NE"
  },
  "entry_22151": {
    "ipa": "vj\u0254\u0308",
    "lat": "6.8047071",
    "tppsr": "vy\u022f",
    "taxon": "St-Gingolph",
    "lon": "46.3931549",
    "canton": "VS"
  },
  "entry_22157": {
    "ipa": "vj\u0153\u0306\u0289\u0349",
    "lat": "7.1147534",
    "tppsr": "vy\u0153\u0306\u0300\u028b\u0331\u0367",
    "taxon": "Fully",
    "lon": "46.1385798",
    "canton": "VS"
  },
  "entry_22172": {
    "ipa": "vi\u02d0\u028e\u00f2\u031d\u0349",
    "lat": "7.0442231",
    "tppsr": "v\u012bl\u032e\u00f2\u0331",
    "taxon": "Montbovon",
    "lon": "46.4882147",
    "canton": "FR"
  },
  "entry_22163": {
    "ipa": "vj\u014f\u031e",
    "lat": "7.4580917",
    "tppsr": "vy\u014f",
    "taxon": "Gr\u00f4ne",
    "lon": "46.2508508",
    "canton": "VS"
  },
  "entry_22158": {
    "ipa": "vj\u00f8y\u0349",
    "lat": "7.3083227",
    "tppsr": "vy\u0153\u0301u\u0331",
    "taxon": "Conthey",
    "lon": "46.2334191",
    "canton": "VS"
  },
  "entry_22150": {
    "ipa": "\u00e3\u0320\u00e7\u028e\u0349\u00e3\u0320",
    "lat": "7.1285556",
    "tppsr": "\u00e3\u00e7\u0311l\u032e\u0331\u00e3",
    "taxon": "Ch\u00e2teau-d'Oex",
    "lon": "46.4732964",
    "canton": "VD"
  },
  "entry_22178": {
    "ipa": "vi\u02d0\u028e\u00f2\u031d\u0349",
    "lat": "7.1134823",
    "tppsr": "v\u012bl\u032e\u00f2\u0331",
    "taxon": "Sugiez",
    "lon": "46.9624815",
    "canton": "FR"
  },
  "entry_22160": {
    "ipa": "vj\u016d",
    "lat": "7.3509003",
    "tppsr": "vy\u028b\u0306",
    "taxon": "Savi\u00e8se",
    "lon": "46.2535376",
    "canton": "VS"
  },
  "french": "(il est) vieux, (elle est) vieille",
  "entry_22153": {
    "ipa": "j\u0153\u0306y\u0349",
    "lat": "6.8693248",
    "tppsr": "y\u0153\u0306\u0300u\u0331",
    "taxon": "Champ\u00e9ry",
    "lon": "46.1778839",
    "canton": "VS"
  },
  "entry_22159": {
    "ipa": "vj\u0254",
    "lat": "7.3047431",
    "tppsr": "vy\u00f2",
    "taxon": "Nendaz",
    "lon": "46.1855093",
    "canton": "VS"
  },
  "entry_22189": {
    "ipa": "v\u025bid\u02b2",
    "lat": "7.250875",
    "tppsr": "v\u00e8id\u032e",
    "taxon": "Orvin",
    "lon": "47.139974",
    "canton": "JU"
  },
  "entry_22135": {
    "ipa": "vi\u02d0\u028eu\u0349",
    "lat": "6.9069294",
    "tppsr": "v\u012bl\u032e\u028b\u0331",
    "taxon": "Chevroux",
    "lon": "46.8883582",
    "canton": "VD"
  },
  "entry_22180": {
    "ipa": "vi\u02d0\u028e",
    "lat": "6.837028",
    "tppsr": "v\u012bl\u032e",
    "taxon": "Boudry",
    "lon": "46.950218",
    "canton": "NE"
  },
  "entry_22143": {
    "ipa": "vi\u02d0j\u00f2\u031d\u0349",
    "lat": "6.5189028",
    "tppsr": "v\u012by\u00f2\u0331",
    "taxon": "Arnex",
    "lon": "46.6980681",
    "canton": "VD"
  },
  "entry_22195": {
    "ipa": "v\u025b\u02d0j",
    "lat": "7.027788",
    "tppsr": "v\u1e15y",
    "taxon": "Cerlatez",
    "lon": "47.243446",
    "canton": "JU"
  },
  "entry_22171": {
    "ipa": "vi\u02d0ju\u0349",
    "lat": "6.9273567",
    "tppsr": "v\u012by\u028b\u0331",
    "taxon": "Semsalves",
    "lon": "46.5731935",
    "canton": "FR"
  },
  "entry_22182": {
    "ipa": "vi\u02d0e\u0349j\u0349",
    "lat": "7.066851",
    "tppsr": "v\u012b\u00e9\u0331y\u0331",
    "taxon": "Landeron",
    "lon": "47.055508",
    "canton": "NE"
  },
  "entry_22162": {
    "ipa": "vj\u014fu\u0349",
    "lat": "7.5473871",
    "tppsr": "vy\u014f\u0301\u028b\u0331",
    "taxon": "Mi\u00e8ge",
    "lon": "46.3119557",
    "canton": "VS"
  },
  "entry_22181": {
    "ipa": "vi\u02d0\u028e",
    "lat": "6.8624613",
    "tppsr": "v\u012bl\u032e",
    "taxon": "Corcelles",
    "lon": "46.9830376",
    "canton": "NE"
  },
  "entry_22137": {
    "ipa": "vi\u02d0\u028e\u025b\u0349",
    "lat": "6.4590043",
    "tppsr": "v\u012bl\u032e\u00e8\u0331",
    "taxon": "L'Auberson",
    "lon": "46.8178516",
    "canton": "VD"
  },
  "entry_22166": {
    "ipa": "vij\u0259\u0349",
    "lat": "6.1235296",
    "tppsr": "viy\u0117\u0331",
    "taxon": "Collex",
    "lon": "46.2761547",
    "canton": "GE"
  },
  "entry_22174": {
    "ipa": "vi\u02d0\u028eu",
    "lat": "7.0698887",
    "tppsr": "v\u012bl\u032e\u028b",
    "taxon": "Avry-sur-Matran",
    "lon": "46.7895993",
    "canton": "FR"
  },
  "entry_22147": {
    "ipa": "vi\u02d0\u028eo\u031d\u0349",
    "lat": "6.536765",
    "tppsr": "v\u012bl\u032eo\u0331",
    "taxon": "Charnex",
    "lon": "46.5613135",
    "canton": "VD"
  },
  "entry_22168": {
    "ipa": "vi\u02d0j",
    "lat": "6.0355571",
    "tppsr": "v\u012by",
    "taxon": "Laconnex",
    "lon": "46.1557721",
    "canton": "GE"
  },
  "entry_22190": {
    "ipa": "ve\u02d0j",
    "lat": "7.284885",
    "tppsr": "v\u1e17y",
    "taxon": "Plagne",
    "lon": "47.1874392",
    "canton": "JU"
  },
  "entry_22187": {
    "ipa": "ve\u02d0\u028eu\u0349",
    "lat": "6.6661454",
    "tppsr": "v\u1e17l\u032e\u028b\u0331",
    "taxon": "Cerneux-P\u00eaquignot",
    "lon": "47.0169066",
    "canton": "NE"
  },
  "entry_22140": {
    "ipa": "vi\u02d0\u028e\u0259\u0349",
    "lat": "6.2585316",
    "tppsr": "v\u012bl\u032e\u0117\u0331",
    "taxon": "Longirod",
    "lon": "46.4944282",
    "canton": "VD"
  },
  "entry_22173": {
    "ipa": "vi\u02d0\u028eo\u031d\u0349",
    "lat": "7.1214922",
    "tppsr": "v\u012bl\u032eo\u0331",
    "taxon": "Arconciel",
    "lon": "46.7473353",
    "canton": "FR"
  },
  "entry_22191": {
    "ipa": "ve\u02d0j",
    "lat": "7.1785922",
    "tppsr": "v\u1e17y",
    "taxon": "Sombeval",
    "lon": "47.1957904",
    "canton": "JU"
  },
  "entry_22167": {
    "ipa": "vi\u02d0j\u022f\u031d\u0349",
    "lat": "6.084291",
    "tppsr": "v\u012by\u022f\u0331",
    "taxon": "Vernier",
    "lon": "46.217026",
    "canton": "GE"
  },
  "entry_22136": {
    "ipa": "vi\u02d0\u028e\u00f2\u031d\u0349",
    "lat": "6.6362255",
    "tppsr": "v\u012bl\u032e\u00f2\u0331",
    "taxon": "Vaugondry",
    "lon": "46.8467152",
    "canton": "VD"
  },
  "entry_22141": {
    "ipa": "vi\u02d0\u028e\u0259\u0349",
    "lat": "6.176213",
    "tppsr": "v\u012bl\u032e\u0117\u0331",
    "taxon": "Commugny",
    "lon": "46.320929",
    "canton": "VD"
  },
  "entry_22149": {
    "ipa": "vi\u02d0\u029f\u0259\u0349",
    "lat": "7.158066",
    "tppsr": "v\u012b\u0142\u0117\u0331",
    "taxon": "Ormont-Dessus",
    "lon": "46.3514789",
    "canton": "VD"
  },
  "entry_22183": {
    "ipa": "vi\u02d0\u025b\u0349j\u0349",
    "lat": "6.956111",
    "tppsr": "v\u012b\u00e8\u0331y\u0331",
    "taxon": "Savagnier",
    "lon": "47.050961",
    "canton": "NE"
  },
  "entry_22155": {
    "ipa": "j\u025e\u0306\u0289\u0349",
    "lat": "7.1463639",
    "tppsr": "y\u0153\u0366\u0306\u028b\u0331\u0367",
    "taxon": "Orsi\u00e8res",
    "lon": "46.0308094",
    "canton": "VS"
  },
  "entry_22148": {
    "ipa": "vi\u02d0\u028e\u00f2\u031d\u0349",
    "lat": "6.9290939",
    "tppsr": "v\u012bl\u032e\u00f2\u0331",
    "taxon": "Roche",
    "lon": "46.3614134",
    "canton": "VD"
  },
  "entry_22154": {
    "ipa": "vj\u00f8\u031ey\u0349",
    "lat": "7.073483",
    "tppsr": "vy\u0153u\u0331",
    "taxon": "Martigny",
    "lon": "46.101706",
    "canton": "VS"
  },
  "entry_22164": {
    "ipa": "vj\u0254\u0306l",
    "lat": "7.4963134",
    "tppsr": "vy\u014f\u0300l",
    "taxon": "\u00c9vol\u00e8ne",
    "lon": "46.1125593",
    "canton": "VS"
  },
  "entry_22139": {
    "ipa": "vj\u00e9\u02d0l\u016d",
    "lat": "6.2358557",
    "tppsr": "vy\u1e17\u0329l\u028b\u0306",
    "taxon": "Le Sentier",
    "lon": "46.6122131",
    "canton": "VD"
  },
  "entry_22169": {
    "ipa": "vj\u0254\u0308",
    "lat": "6.1832454",
    "tppsr": "vy\u022f",
    "taxon": "Veyrier",
    "lon": "46.16778",
    "canton": "GE"
  },
  "entry_22145": {
    "ipa": "v\u026a\u02d0\u028e\u00f2\u031d\u0349",
    "lat": "6.7383916",
    "tppsr": "v\u012b\u0300l\u032e\u00f2\u0331",
    "taxon": "Prahins",
    "lon": "46.7331778",
    "canton": "VD"
  },
  "entry_22170": {
    "ipa": "vj\u0254\u0308",
    "lat": "6.244375",
    "tppsr": "vy\u022f",
    "taxon": "Hermance",
    "lon": "46.302258",
    "canton": "GE"
  },
  "entry_22185": {
    "ipa": "vi\u02d0\u028e\u00f2\u031d\u0349",
    "lat": "6.7246751",
    "tppsr": "v\u012bl\u032e\u00f2\u0331",
    "taxon": "Noiraigue",
    "lon": "46.9562832",
    "canton": "NE"
  },
  "entry_22175": {
    "ipa": "vi\u02d0ju\u0349",
    "lat": "7.1238357",
    "tppsr": "v\u012by\u028b\u0331",
    "taxon": "Courtepin",
    "lon": "46.8652994",
    "canton": "FR"
  },
  "entry_22146": {
    "ipa": "vi\u02d0\u028eu\u0349",
    "lat": "6.742199",
    "tppsr": "v\u012bl\u032e\u028b\u0331",
    "taxon": "Montpreveyres",
    "lon": "46.582048",
    "canton": "VD"
  },
  "entry_22192": {
    "ipa": "ve\u02d0j",
    "lat": "7.3367958",
    "tppsr": "v\u1e17y",
    "taxon": "Court",
    "lon": "47.239562",
    "canton": "JU"
  }
}